{"abl": {"able": {"a": 1, "b": 1, "l": 1, "e": 1}}, "aci": {"acity": {"a": 1, "c": 1, "i": 1, "t": 1, "y": 1}}, "oci": {"ocity": {"o": 1, "c": 1, "i": 1, "t": 1, "y": 1}}, "ade": {"ade": {"a": 1, "d": 1, "e": 1}}, "age": {"age": {"a": 1, "g": 1, "e": 1}}, "aho": {"aholic": {"a": 1, "h": 1, "o": 1, "l": 1, "i": 1, "c": 1}}, "alg": {"algia": {"a": 2, "l": 1, "g": 1, "i": 1}}, "anc": {"ance": {"a": 1, "n": 1, "c": 1, "e": 1}}, "ant": {"ant": {"a": 1, "n": 1, "t": 1}}, "ard": {"ard": {"a": 1, "r": 1, "d": 1}}, "ari": {"arian": {"a": 2, "r": 1, "i": 1, "n": 1}, "arium": {"a": 1, "r": 1, "i": 1, "u": 1, "m": 1}}, "ori": {"orium": {"o": 1, "r": 1, "i": 1, "u": 1, "m": 1}}, "ary": {"ary": {"a": 1, "r": 1, "y": 1}}, "ate": {"ate": {"a": 1, "t": 1, "e": 1}}, "ati": {"ation": {"a": 1, "t": 1, "i": 1, "o": 1, "n": 1}, "ative": {"a": 1, "t": 1, "i": 1, "v": 1, "e": 1}}, "cid": {"cide": {"c": 1, "i": 1, "d": 1, "e": 1}}, "cra": {"cracy": {"c": 2, "r": 1, "a": 1, "y": 1}, "crat": {"c": 1, "r": 1, "a": 1, "t": 1}}, "cul": {"cule": {"c": 1, "u": 1, "l": 1, "e": 1}}, "cyc": {"cycle": {"c": 2, "y": 1, "l": 1, "e": 1}}, "dom": {"dom": {"d": 1, "o": 1, "m": 1}}, "dox": {"dox": {"d": 1, "o": 1, "x": 1}}, "ect": {"ectomy": {"e": 1, "c": 1, "t": 1, "o": 1, "m": 1, "y": 1}}, "eer": {"eer": {"e": 2, "r": 1}}, "emi": {"emia": {"e": 1, "m": 1, "i": 1, "a": 1}}, "enc": {"ence": {"e": 2, "n": 1, "c": 1}, "ency": {"e": 1, "n": 1, "c": 1, "y": 1}}, "ent": {"ent": {"e": 1, "n": 1, "t": 1}}, "ern": {"ern": {"e": 1, "r": 1, "n": 1}}, "esc": {"escence": {"e": 3, "s": 1, "c": 2, "n": 1}}, "ese": {"ese": {"e": 2, "s": 1}}, "esq": {"esque": {"e": 2, "s": 1, "q": 1, "u": 1}}, "ess": {"ess": {"e": 1, "s": 2}}, "est": {"est": {"e": 1, "s": 1, "t": 1}}, "eti": {"etic": {"e": 1, "t": 1, "i": 1, "c": 1}}, "ett": {"ette": {"e": 2, "t": 2}}, "ful": {"ful": {"f": 1, "u": 1, "l": 1}}, "gam": {"gam/gamy": {"g": 2, "a": 2, "m": 2, "/": 1, "y": 1}}, "gon": {"gon/gonic": {"g": 2, "o": 2, "n": 2, "/": 1, "i": 1, "c": 1}}, "hoo": {"hood": {"h": 1, "o": 2, "d": 1}}, "ial": {"ial": {"i": 1, "a": 1, "l": 1}}, "ian": {"ian": {"i": 1, "a": 1, "n": 1}}, "ias": {"iasis": {"i": 2, "a": 1, "s": 2}}, "iat": {"iatric": {"i": 2, "a": 1, "t": 1, "r": 1, "c": 1}}, "ibl": {"ible": {"i": 1, "b": 1, "l": 1, "e": 1}}, "ic/": {"ic/ical": {"i": 2, "c": 2, "/": 1, "a": 1, "l": 1}}, "ile": {"ile": {"i": 1, "l": 1, "e": 1}}, "ily": {"ily": {"i": 1, "l": 1, "y": 1}}, "ine": {"ine": {"i": 1, "n": 1, "e": 1}}, "ing": {"ing": {"i": 1, "n": 1, "g": 1}}, "ion": {"ion": {"i": 1, "o": 1, "n": 1}}, "iou": {"ious": {"i": 1, "o": 1, "u": 1, "s": 1}}, "ish": {"ish": {"i": 1, "s": 1, "h": 1}}, "ism": {"ism": {"i": 1, "s": 1, "m": 1}}, "ist": {"ist": {"i": 1, "s": 1, "t": 1}}, "ite": {"ite": {"i": 1, "t": 1, "e": 1}}, "iti": {"itis": {"i": 2, "t": 1, "s": 1}}, "ity": {"ity": {"i": 1, "t": 1, "y": 1}}, "ive": {"ive": {"i": 1, "v": 1, "e": 1}}, "iza": {"ization": {"i": 2, "z": 1, "a": 1, "t": 1, "o": 1, "n": 1}}, "ize": {"ize": {"i": 1, "z": 1, "e": 1}}, "les": {"less": {"l": 1, "e": 1, "s": 2}}, "let": {"let": {"l": 1, "e": 1, "t": 1}}, "lik": {"like": {"l": 1, "i": 1, "k": 1, "e": 1}}, "lin": {"ling": {"l": 1, "i": 1, "n": 1, "g": 1}}, "log": {"loger/logist": {"l": 2, "o": 2, "g": 2, "e": 1, "r": 1, "/": 1, "i": 1, "s": 1, "t": 1}, "log": {"l": 1, "o": 1, "g": 1}}, "men": {"ment": {"m": 1, "e": 1, "n": 1, "t": 1}}, "nes": {"ness": {"n": 1, "e": 1, "s": 2}}, "oid": {"oid": {"o": 1, "i": 1, "d": 1}}, "olo": {"ology": {"o": 2, "l": 1, "g": 1, "y": 1}}, "oma": {"oma": {"o": 1, "m": 1, "a": 1}}, "ony": {"onym": {"o": 1, "n": 1, "y": 1, "m": 1}}, "opi": {"opia": {"o": 1, "p": 1, "i": 1, "a": 1}}, "ops": {"opsy": {"o": 1, "p": 1, "s": 1, "y": 1}}, "ory": {"ory": {"o": 1, "r": 1, "y": 1}}, "osi": {"osis": {"o": 1, "s": 2, "i": 1}}, "ost": {"ostomy/otomy": {"o": 4, "s": 1, "t": 2, "m": 2, "y": 2, "/": 1}}, "ous": {"ous": {"o": 1, "u": 1, "s": 1}}, "pat": {"path": {"p": 1, "a": 1, "t": 1, "h": 1}, "pathy": {"p": 1, "a": 1, "t": 1, "h": 1, "y": 1}}, "phi": {"phile": {"p": 1, "h": 1, "i": 1, "l": 1, "e": 1}}, "pho": {"phobia": {"p": 1, "h": 1, "o": 1, "b": 1, "i": 1, "a": 1}, "phone": {"p": 1, "h": 1, "o": 1, "n": 1, "e": 1}}, "phy": {"phyte": {"p": 1, "h": 1, "y": 1, "t": 1, "e": 1}}, "ple": {"plegia": {"p": 1, "l": 1, "e": 1, "g": 1, "i": 1, "a": 1}, "plegic": {"p": 1, "l": 1, "e": 1, "g": 1, "i": 1, "c": 1}}, "pne": {"pnea": {"p": 1, "n": 1, "e": 1, "a": 1}}, "scr": {"scribe/script": {"s": 2, "c": 2, "r": 2, "i": 2, "b": 1, "e": 1, "/": 1, "p": 1, "t": 1}}, "sec": {"sect": {"s": 1, "e": 1, "c": 1, "t": 1}}, "shi": {"ship": {"s": 1, "h": 1, "i": 1, "p": 1}}, "sio": {"sion": {"s": 1, "i": 1, "o": 1, "n": 1}}, "som": {"some": {"s": 1, "o": 1, "m": 1, "e": 1}}, "sop": {"sophy/sophic": {"s": 2, "o": 2, "p": 2, "h": 2, "y": 1, "/": 1, "i": 1, "c": 1}}, "tio": {"tion": {"t": 1, "i": 1, "o": 1, "n": 1}}, "tom": {"tome/tomy": {"t": 2, "o": 2, "m": 2, "e": 1, "/": 1, "y": 1}}, "tro": {"trophy": {"t": 1, "r": 1, "o": 1, "p": 1, "h": 1, "y": 1}}, "tud": {"tude": {"t": 1, "u": 1, "d": 1, "e": 1}}, "ula": {"ular": {"u": 1, "l": 1, "a": 1, "r": 1}}, "uou": {"uous": {"u": 2, "o": 1, "s": 1}}, "ure": {"ure": {"u": 1, "r": 1, "e": 1}}, "war": {"ward": {"w": 1, "a": 1, "r": 1, "d": 1}, "ware": {"w": 1, "a": 1, "r": 1, "e": 1}}, "wis": {"wise": {"w": 1, "i": 1, "s": 1, "e": 1}}}